[
  {
    "tag_name": "entity",
    "ids_to_tags": {
      "1": "B-age",
      "2": "I-age",
      "3": "L-age",
      "4": "U-age",
      "5": "B-disease",
      "6": "I-disease",
      "7": "L-disease",
      "8": "U-disease",
      "9": "B-mobile",
      "10": "I-mobile",
      "11": "L-mobile",
      "12": "U-mobile",
      "13": "B-name",
      "14": "I-name",
      "15": "L-name",
      "16": "U-name",
      "17": "B-slot",
      "18": "I-slot",
      "19": "L-slot",
      "20": "U-slot",
      "0": "O"
    },
    "tags_to_ids": {
      "B-age": 1,
      "I-age": 2,
      "L-age": 3,
      "U-age": 4,
      "B-disease": 5,
      "I-disease": 6,
      "L-disease": 7,
      "U-disease": 8,
      "B-mobile": 9,
      "I-mobile": 10,
      "L-mobile": 11,
      "U-mobile": 12,
      "B-name": 13,
      "I-name": 14,
      "L-name": 15,
      "U-name": 16,
      "B-slot": 17,
      "I-slot": 18,
      "L-slot": 19,
      "U-slot": 20,
      "O": 0
    },
    "num_tags": 21
  }
]